geffnet/__init__.py
geffnet/config.py
geffnet/conv2d_layers.py
geffnet/efficientnet_builder.py
geffnet/gen_efficientnet.py
geffnet/helpers.py
geffnet/mobilenetv3.py
geffnet/model_factory.py
geffnet/version.py
geffnet/activations/__init__.py
geffnet/activations/activations.py
geffnet/activations/activations_jit.py
geffnet/activations/activations_me.py
geffnet-1.0.2.dist-info/LICENSE
geffnet-1.0.2.dist-info/METADATA
geffnet-1.0.2.dist-info/WHEEL
geffnet-1.0.2.dist-info/top_level.txt
geffnet-1.0.2.dist-info/RECORD
